couchdb_docker_apis/__init__.py
couchdb_docker_apis/couchdb_docker_api.py
couchdb_rest_api-0.12.dist-info/METADATA
couchdb_rest_api-0.12.dist-info/RECORD
couchdb_rest_api-0.12.dist-info/WHEEL
couchdb_rest_api-0.12.dist-info/top_level.txt
couchdb_rest_apis/__init__.py
couchdb_rest_apis/couchdb_rest_api.py
