Metadata-Version: 2.1
Name: couchdb-rest-api
Version: 0.12
Summary: CouchDB REST API
Home-page: https://magengit.github.io/
Author: Reinaldo Penno
Author-email: rapenno@gmail.com
License: Apache Software License
Platform: UNKNOWN
Classifier: Development Status :: 2 - Pre-Alpha
Classifier: Intended Audience :: Education
Classifier: Intended Audience :: Financial and Insurance Industry
Classifier: Intended Audience :: Healthcare Industry
Classifier: Intended Audience :: Legal Industry
Classifier: Topic :: Security
Classifier: License :: OSI Approved :: Apache Software License
Classifier: Programming Language :: Python :: 3.6
Requires-Dist: coverage (>=4.5.1)
Requires-Dist: docker (>=3.3.0)
Requires-Dist: flake8 (>=3.3.0)
Requires-Dist: pymongo (>=3.4.0)
Requires-Dist: pytest (>=3.4.0)
Requires-Dist: responses (>=0.5.1)
Requires-Dist: Sphinx (>=1.6.3)
Requires-Dist: wheel (>=0.30.0a0)
Requires-Dist: magen-logger (>=1.0a1)
Requires-Dist: magen-utils (>=1.2a2)
Requires-Dist: magen-rest-service (>=1.3a10)
